zthreadpool.py
zthreadpool-1.0.1.dist-info/LICENSE
zthreadpool-1.0.1.dist-info/METADATA
zthreadpool-1.0.1.dist-info/WHEEL
zthreadpool-1.0.1.dist-info/top_level.txt
zthreadpool-1.0.1.dist-info/RECORD
