Metadata-Version: 2.1
Name: zthreadpool
Version: 1.0.1
Summary: 线程池, 固定指定数量的线程来执行任务, 避免重复创建和销毁线程时的资源消耗
Home-page: https://pypi.org/
Author: zlyuan
Author-email: 1277260932@qq.com
License: GNU GENERAL PUBLIC LICENSE
Platform: all
Classifier: Environment :: Web Environment
Classifier: Intended Audience :: Developers
Classifier: Operating System :: OS Independent
Classifier: Programming Language :: Python
Classifier: Programming Language :: Python :: 3
Classifier: Programming Language :: Python :: 3.5
Classifier: Programming Language :: Python :: 3.6
Requires-Dist: zqueue (>=1.2.0)
Requires-Dist: zblocker
